EskomAPI/__init__.py
EskomAPI/eskom.py
EskomAPI-0.0.3.dist-info/LICENSE
EskomAPI-0.0.3.dist-info/METADATA
EskomAPI-0.0.3.dist-info/WHEEL
EskomAPI-0.0.3.dist-info/top_level.txt
EskomAPI-0.0.3.dist-info/RECORD
