Metadata-Version: 2.1
Name: EskomAPI
Version: 0.0.3
Summary: Eskom RestAPI for LoadShedding in Python
Home-page: https://adgstudios.co.za
Author: Ashlin Darius Govindasamy
Author-email: adgrules@hotmail.com
License: MIT
Platform: UNKNOWN
Classifier: Programming Language :: Python :: 3
Classifier: License :: OSI Approved :: MIT License
Classifier: Operating System :: OS Independent
Requires-Dist: requests
Requires-Dist: beautifulsoup4
